vfd_display/__init__.py
vfd_display/vfd_display.py
vfd_display-1.1.2.dist-info/METADATA
vfd_display-1.1.2.dist-info/WHEEL
vfd_display-1.1.2.dist-info/top_level.txt
vfd_display-1.1.2.dist-info/RECORD
