Metadata-Version: 2.1
Name: vfd-display
Version: 1.1.2
Summary: A module to interface with VFD displays via serial communication.
Home-page: https://github.com/mnedev-cell/vfd-display
Author: DEVMNE
Author-email: mne@yaposarl.ma
Classifier: Programming Language :: Python :: 3
Classifier: License :: OSI Approved :: MIT License
Classifier: Operating System :: OS Independent
Requires-Python: >=3.6
Requires-Dist: pyserial
